{
  "id": "afaf4ddd-0b71-4901-92b0-73fc1055a67e",
  "prevId": "465ee224-17a6-47fe-a88f-be648c52fdc1",
  "version": "7",
  "dialect": "postgresql",
  "tables": {
    "public.trips": {
      "name": "trips",
      "schema": "",
      "columns": {
        "id": {
          "name": "id",
          "type": "serial",
          "primaryKey": true,
          "notNull": true
        },
        "name": {
          "name": "name",
          "type": "text",
          "primaryKey": false,
          "notNull": false
        },
        "description": {
          "name": "description",
          "type": "text",
          "primaryKey": false,
          "notNull": false
        },
        "durationDays": {
          "name": "durationDays",
          "type": "integer",
          "primaryKey": false,
          "notNull": false
        },
        "durationNights": {
          "name": "durationNights",
          "type": "integer",
          "primaryKey": false,
          "notNull": false
        },
        "price": {
          "name": "price",
          "type": "integer",
          "primaryKey": false,
          "notNull": false
        },
        "deposit": {
          "name": "deposit",
          "type": "integer",
          "primaryKey": false,
          "notNull": false
        },
        "date": {
          "name": "date",
          "type": "text[]",
          "primaryKey": false,
          "notNull": false
        },
        "includes": {
          "name": "includes",
          "type": "text[]",
          "primaryKey": false,
          "notNull": false
        },
        "location": {
          "name": "location",
          "type": "text",
          "primaryKey": false,
          "notNull": false
        },
        "imageUrl": {
          "name": "imageUrl",
          "type": "text",
          "primaryKey": false,
          "notNull": false
        },
        "galleryImages": {
          "name": "galleryImages",
          "type": "text[]",
          "primaryKey": false,
          "notNull": false
        },
        "active": {
          "name": "active",
          "type": "boolean",
          "primaryKey": false,
          "notNull": false
        },
        "status": {
          "name": "status",
          "type": "text",
          "primaryKey": false,
          "notNull": false
        },
        "availableSlots": {
          "name": "availableSlots",
          "type": "integer",
          "primaryKey": false,
          "notNull": false
        },
        "capacity": {
          "name": "capacity",
          "type": "integer",
          "primaryKey": false,
          "notNull": false
        },
        "createdAt": {
          "name": "createdAt",
          "type": "timestamp",
          "primaryKey": false,
          "notNull": false,
          "default": "now()"
        },
        "updatedAt": {
          "name": "updatedAt",
          "type": "timestamp",
          "primaryKey": false,
          "notNull": false,
          "default": "now()"
        }
      },
      "indexes": {},
      "foreignKeys": {},
      "compositePrimaryKeys": {},
      "uniqueConstraints": {}
    }
  },
  "enums": {},
  "schemas": {},
  "_meta": {
    "columns": {},
    "schemas": {},
    "tables": {}
  }
}